test_package/__init__.py
test_package/python_file_0.py
test_package_username-0.1.dist-info/METADATA
test_package_username-0.1.dist-info/WHEEL
test_package_username-0.1.dist-info/top_level.txt
test_package_username-0.1.dist-info/RECORD
