Metadata-Version: 2.1
Name: test-package-username
Version: 0.1
Summary: This is a test package.
Author: hassan
Author-email: hmansoor2@slb.com
Classifier: Programming Language :: Python :: 3
Classifier: License :: OSI Approved :: MIT License
Classifier: Operating System :: OS Independent
Requires-Python: >=3.5
